setup.py
controlspeed/__init__.py
controlspeed/local_mutex.py
controlspeed/utils.py
controlspeed.egg-info/PKG-INFO
controlspeed.egg-info/SOURCES.txt
controlspeed.egg-info/dependency_links.txt
controlspeed.egg-info/requires.txt
controlspeed.egg-info/top_level.txt